Metadata-Version: 2.1
Name: deutils
Version: 0.0.1
Summary: includes Google Cloud, AWS, Snowflake, PySpark and some data manipulation functions
Home-page: UNKNOWN
Author: Weiang Li
Author-email: weiangli1995@gmail.com
License: MIT
Platform: UNKNOWN
Classifier: Development Status :: 3 - Alpha
Classifier: Intended Audience :: Developers
Classifier: Operating System :: Microsoft :: Windows :: Windows 10
Classifier: License :: OSI Approved :: MIT License
Classifier: Programming Language :: Python :: 3
License-File: LICENCE.txt
